specargs/__init__.py
specargs/apispec.py
specargs/common.py
specargs/decorators.py
specargs/framework/__init__.py
specargs/framework/bottle.py
specargs/framework/django.py
specargs/framework/flask.py
specargs/framework/tornado.py
specargs/in_poly.py
specargs/oas.py
specargs/plugin.py
specargs/validate.py
specargs/view_response.py
specargs-0.1.0.dist-info/LICENSE
specargs-0.1.0.dist-info/WHEEL
specargs-0.1.0.dist-info/METADATA
specargs-0.1.0.dist-info/RECORD
